{
  "count1": 3, //战士3铭文
  "group1": {
    "1": { //基本剑术
      "133": 0.3, //基本剑术【旋风印】
      "134": 0.4, //基本剑术【主宰印】
      "135": 0.1, //基本剑术【幽速印】
      "136": 0.2 //基本剑术【压制印】
    },
    "2": { //攻杀剑术
      "137": 0.6, //攻杀剑术【银光印】
      "138": 0.3, //攻杀剑术【暴君印】
      "139": 0.05, //攻杀剑术【血杀印】
      "140": 0.05 //攻杀剑术【煌龙印】
    },
    "3": { //刺杀剑术
      "141": 0.2, //刺杀剑术【耀光印】
      "142": 0.8 //刺杀剑术【破山印】
    },
    "4": { //半月弯刀
      "143": 0.65, //半月弯刀【月华印】
      "144": 0.25, //半月弯刀【观月印】
      "145": 0.1 //半月弯刀【疾月印】
    },
    "5": { //野蛮冲撞
      "146": 0.15, //野蛮冲撞【裂风印】
      "147": 0.05, //野蛮冲撞【聚火印】
      "148": 0.05, //野蛮冲撞【疾步印】
      "149": 0.30, //野蛮冲撞【冲撞印】
      "150": 0.45 //野蛮冲撞【蛮勇印】
    },
    "6": { //烈火剑法
      "151": 0.45, //烈火剑法【斩月印】
      "152": 0.5, //烈火剑法【夺火印】
      "153": 0.05 //烈火剑法【燃烧印】
    },
    "7": { //翔空剑法
      "154": 0.5, //翔空剑法【开疆印】
      "155": 0.3, //翔空剑法【神躯印】
      "156": 0.2 //翔空剑法【升龙印】
    },
    "8": { //莲月剑法
      "161": 0.75, //十方斩【增强印】
      "162": 0.25 //十方斩【强大印】
    },
    "9": { //快刀斩马
      "163": 0.5, //快刀斩马【刀法印】
      "164": 0.3, //快刀斩马【快刀印】
      "165": 0.2 //快刀斩马【霸刀印】
    },
    "10": { //天雷锤
      "166": 0.8, //天雷锤【锤子印】
      "167": 0.15, //天雷锤【战锤印】
      "168": 0.05 //天雷锤【天神印】
    },
    "11": { //铁布衫
      "169": 0.75, //铁布衫【健壮印】
      "170": 0.25 //铁布衫【贴布印】
    },
    "12": { //乾坤大挪移
      "171": 1 //乾坤大挪移【挪移印】
    },
    "13": { //斗转星移
      "172": 1 //斗转星移【斗转印】
    },
    "14": { //破血狂杀
      "173": 0.1, //破血狂杀【破血印】
      "174": 0.9 //破血狂杀【狂魔印】
    },
    "15": { //金刚之躯
      "175": 0.55, //金刚之躯【金刚印】
      "176": 0.45 //金刚之躯【苏铭印】
    },
    "16": { //移花接木
      "177": 0.55, //移花接木【敬畏印】
      "178": 0.45 //移花接木【回声印】
    },
    "17": { //挑衅
      "197": 0.7, //挑衅【心眼印】
      "198": 0.2, //挑衅【虚空印】
      "199": 0.1 //挑衅【狩猎印】
    },
    "18": { //泰山压顶
      "177": 0.75, //泰山压顶【调和印】
      "178": 0.25 //泰山压顶【怜悯印】
    },
    "19": { //莲月剑法
      "157": 0.95, //莲月剑法【莲月印】
      "158": 0.05 //莲月剑法【无双印】
    }
  },
  "count2": 3, //法师3铭文
  "group2": {
    "1": { //火球术
      "91": 0.9, //火球术【火锥印】
      "92": 0.1 //火球术【火球印】
    },
    "2": { //霹雳掌
      "93": 0.6, //霹雳掌【超凡印】
      "94": 0.4 //霹雳掌【异端印】
    },
    "3": { //冰月神掌
      "95": 0.9, //冰月神掌【冰雪印】
      "96": 0.1 //冰月神掌【冰强印】
    },
    "4": { //抗拒火环
      "98": 0.1, //抗拒火环【焰华印】
      "99": 0.9 //抗拒火环【火环印】
    },
    "5": { //诱惑之光
      "100": 0.1, //诱惑之光【军势印】
      "101": 0.4, //诱惑之光【魔语印】
      "102": 0.4, //诱惑之光【魔魇印】
      "103": 0.1 //诱惑之光【血契印】
    },
    "6": { //瞬息移动
      "104": 0.8, //瞬息移动【移动印】
      "196": 0.2 //瞬息移动【移速印】
    },
    "7": { //大火球
      "105": 0.7, //大火球【训诫印】
      "106": 0.2, //大火球【堕落印】
      "107": 0.1 //大火球【触媒印】
    },
    "8": { //雷电术
      "108": 0.3, //雷电术【天罚印】
      "109": 0.15, //雷电术【天怒印】
      "110": 0.55 //雷电术【不灭印】
    },
    "9": { //冰月震天
      "111": 1 //冰月震天【弧光印】
    },
    "10": { //击风
      "112": 1 //击风【静默印】
    },
    "11": { //地狱火
      "113": 1 //地狱火【炎龙印】
    },
    "12": { //疾光电影
      "114": 0.6, //疾光电影【雷神印】
      "115": 0.35, //疾光电影【雷诛印】
      "116": 0.05 //疾光电影【雷咒印】
    },
    "13": { //冰沙掌
      "117": 0.25, //冰沙掌【冰刀印】
      "118": 0.75 //冰沙掌【冰霜印】 
    },
    "14": { //风震天
      "119": 0.2, //风震天【风波印】
      "120": 0.8 //风震天【山风印】
    },
    "15": { //火墙
      "121": 0.8, //火墙【观火印】
      "122": 0.2 //火墙【真红印】
    },
    "16": { //圣言术
      "123": 0.15, //圣言术【圣灵印】
      "124": 0.85 //圣言术【秘咒印】
    },
    "17": { //移形换位
      "125": 1 //移形换位【移行印】
    },
    "18": { //魔法盾
      "126": 0.7, //魔法盾【天守印】
      "127": 0.15, //魔法盾【霜骨印】
      "128": 0.15 //魔法盾【逢生印】
    },
    "19": { //爆裂火焰
      "129": 1 //爆裂火焰【疾火印】
    },
    "20": { //地狱雷光
      "130": 1 //地狱雷光【雷龙印】
    },
    "21": { //冰咆哮
      "131": 0.8, //冰咆哮【龙行印】
      "132": 0.2 //冰咆哮【龙魂印】
    },
    "22": { //焰天火雨
      "179": 0.7, //焰天火雨【焰天印】
      "180": 0.2, //焰天火雨【群火印】
      "181": 0.1 //焰天火雨【爆火印】
    },
    "23": { //天之怒火
      "182": 0.8, //天之怒火【圣人印】
      "183": 0.2 //天之怒火【怒火印】
    },
    "24": { //魄冰刺
      "184": 0.8, //魄冰刺【冰刺印】
      "185": 0.2 //魄冰刺【冰花印】
    },
    "25": { //护身冰环
      "186": 0.7, //护身冰环【冰神印】
      "187": 0.3 //护身冰环【冰环印】
    },
    "26": { //怒神霹雳
      "188": 1 //怒神霹雳【霹雳印】
    },
    "27": { //天打雷劈
      "189": 0.8, //天打雷劈【正义印】
      "190": 0.2 //天打雷劈【反击印】
    },
    "28": { //闪电雷鸣
      "191": 1 //闪电雷鸣【命中印】
    },
    "29": { //龙卷风
      "192": 0.8, //龙卷风【风暴印】
      "193": 0.2 //龙卷风【暴风印】
    },
    "30": { //旋风墙
      "194": 0.8, //旋风墙【崩坏印】
      "195": 0.2 //旋风墙【风怒印】
    }
  },
  "count3": 3, //道士3铭文
  "group3": {
    "1": { //治愈术
      "2": 0.75, //治愈术【神术印】
      "3": 0.15, //治愈术【神宝印】
      "4": 0.1 //治愈术【妙手印】
    },
    "2": { //精神力战法
      "5": 0.75, //精神力战法【灵击印】
      "6": 0.2, //精神力战法【道法印】
      "7": 0.05 //精神力战法【灵爆印】
    },
    "3": { //施毒术
      "8": 0.15, //施毒术【凌波印】
      "9": 0.65, //施毒术【凌锋印】
      "10": 0.1, //施毒术【凌云印】
      "11": 0.1 //施毒术【凌蛊印】
    },
    "4": { //灵魂火符
      "12": 0.5, //灵魂火符【火蛇印】
      "13": 0.1, //灵魂火符【弹射印】
      "68": 0.05, //灵魂火符【群射印】
      "14": 0.3, //灵魂火符【灵控印】
      "15": 0.05 //灵魂火符【符阵印】
    },
    "5": { //月魂断玉
      "16": 0.25, //月魂断玉【玉龙印】
      "17": 0.75 //月魂断玉【龙王印】
    },
    "6": { //召唤骷髅
      "18": 0.15, //召唤骷髅【君王印】
      "19": 0.15, //召唤骷髅【偷天印】
      "20": 0.7 //召唤骷髅【迦兰印】
    },
    "7": { //隐身术
      "21": 0.1, //隐身术【空相印】
      "22": 0.9 //隐身术【流星印】
    },
    "8": { //幽灵盾
      "23": 0.3, //幽灵盾【灵携印】
      "24": 0.6, //幽灵盾【灵保印】
      "25": 0.1 //幽灵盾【幽强印】
    },
    "9": { //集体隐身术
      "26": 0.9, //集体隐身术【影集印】
      "27": 0.1 //集体隐身术【集中印】
    },
    "10": { //月魂灵波
      "28": 0.5, //月魂灵波【毒蛇印】
      "29": 0.25, //月魂灵波【蛇射印】
      "69": 0.05, //月魂灵波【枪射印】
      "30": 0.15, //月魂灵波【魂控印】
      "31": 0.05 //月魂灵波【魂阵印】
    },
    "11": { //神圣战甲术
      "32": 0.15, //神圣战甲术【凝丹印】
      "33": 0.75, //神圣战甲术【凝保印】
      "34": 0.1 //神圣战甲术【凝效印】
    },
    "12": { //困魔咒
      "35": 0.1, //困魔咒【邪咒印】
      "36": 0.9 //困魔咒【正咒印】
    },
    "13": { //空拳刀法
      "37": 0.55, //空拳刀法【空拳印】
      "38": 0.35, //空拳刀法【拳霸印】
      "39": 0.1 //空拳刀法【拳击印】
    },
    "14": { //强魔震法
      "40": 0.1, //强魔震法【强法印】
      "41": 0.9 //强魔震法【强保印】
    },
    "15": { //召唤神兽
      "42": 0.75, //召唤神兽【灵兽印】
      "43": 0.15, //召唤神兽【血兽印】
      "44": 0.1 //召唤神兽【圣兽印】
    },
    "16": { //群体治愈术
      "45": 1 //群体治愈术【瑶光印】
    },
    "17": { //超强召唤骷髅
      "46": 0.1, //超强召唤骷髅【君王印】
      "47": 0.15, //超强召唤骷髅【偷天印】
      "48": 0.75 //超强召唤骷髅【迦兰印】
    },
    "18": { //猛虎强势
      "49": 0.9, //猛虎强势【猛士印】
      "50": 0.1 //猛虎强势【强势印】
    },
    "19": {
      "51": 0.85, //回生术【保护印】
      "52": 0.15 //回生术【道尊印】
    },
    "20": { //移花接玉
      "53": 0.6, //移花接玉【接速印】
      "54": 0.4 //移花接玉【轮回印】
    },
    "21": { //妙影无踪【踪保印】
      "55": 0.85, //妙影无踪【踪保印】
      "70": 0.15 //妙影无踪【妙影印】
    },
    "22": { //灭魂火符
      "56": 0.5, //灭魂火符【速射印】
      "57": 0.25, //灭魂火符【爆射印】
      "58": 0.15, //灭魂火符【灭魂印】
      "59": 0.05, //灭魂火符【灭阵印】
      "71": 0.05 //灭魂火符【弓射印】
    },
    "23": { //炎魔召唤术
      "60": 0.50, //炎魔召唤术【红月印】
      "61": 0.25, //炎魔召唤术【火焰印】
      "62": 0.25 //炎魔召唤术【真强印】
    },
    "24": { //魔焰强解术
      "63": 0.75, //魔焰强解术【凶兆印】
      "64": 0.15, //魔焰强解术【祸源印】
      "65": 0.1 //魔焰强解术【宿命印】
    },
    "25": { //传染
      "66": 0.85, //传染【射手印】
      "67": 0.15 //传染【传射印】
    },
    "26": { //云寂术
      "72": 1 //云寂术【云寂印】
    },
    "27": { //阴阳法环
      "73": 0.55, //阴阳法环【吸血印】
      "74": 0.3, //阴阳法环【法环印】
      "75": 0.15 //阴阳法环【饮血印】
    },
    "28": { //吸星大法
      "76": 0.65, //吸星大法【吸星印】
      "77": 0.2, //吸星大法【血饮印】
      "78": 0.15 //吸星大法【咒语印】
    },
    "29": { //地狱回疗
      "79": 1 //地狱回疗【地狱印】
    }
  },
  "count4": 3, //刺客3铭文
  "group4": {
    "1": { //垂柳舞
      "202": 1 //垂柳舞【长生印】
    },
    "2": { //蔓藤舞
      "203": 1 //蔓藤舞【夺萃印】
    },
    "3": { //磨炼
      "204": 0.9, //磨炼【隐匿印】
      "205": 0.1  //磨炼【贪婪印】
    },
    "4": { //毒云
      "206": 0.9, //毒云【灵山印】
      "207": 0.1 //毒云【均衡印】
    },
    "5": { //盛开
      "208": 0.7, //盛开【冥想印】
      "209": 0.2, //盛开【纷争印】
      "210": 0.1 //盛开【异变印】
    },
    "6": { //白莲
      "211": 0.7, //白莲【野性印】
      "212": 0.2, //白莲【潜能印】
      "213": 0.1 //白莲【侵蚀印】
    },
    "7": { //满月恶狼
      "214": 1 //满月恶狼【献祭印】
    },
    "8": { //亡灵束缚
      "215": 1 //亡灵束缚【憎恶印】
    },
    "9": { //红莲
      "216": 0.7, //红莲【庇护印】
      "217": 0.2, //红莲【奇袭印】
      "218": 0.1 //红莲【无畏印】
    },
    "10": { //烈焰
      "219": 0.7, //烈焰【铁躯印】
      "220": 0.2, //烈焰【滋生印】
      "221": 0.1 //烈焰【吞噬印】
    },
    "11": { //血禅
      "222": 1 //血禅【急救印】
    },
    "12": { //血之盟约
      "223": 1 //血之盟约【渴血印】
    },
    "13": { //月季
      "224": 0.75, //月季【复苏印】
      "225": 0.2, //月季【刹那印】
      "226": 0.05 //月季【惩戒印】
    },
    "14": { //亡灵替身
      "227": 0.8, //亡灵替身【气数印】
      "228": 0.2 //亡灵替身【狂热印】
    },
    "15": { //孽报
      "229": 0.7, //孽报【阳炎印】
      "230": 0.2, //孽报【戒律印】
      "231": 0.1 //孽报【荆棘印】
    },
    "16": { //神机妙算
      "232": 1 //神机妙算【暴戾印】
    },
    "17": { //深渊
      "233": 1 //深渊【衰败印】
    },
    "18": { //新月爆炎龙
      "234": 0.85, //新月爆炎龙【突进印】
      "235": 0.1, //新月爆炎龙【收割印】
      "236": 0.05 //新月爆炎龙【破魔印】
    },
    "19": { //百花盛开
      "237": 1 //百花盛开【贯穿印】
    },
    "20": { //鹰击
      "238": 0.6, //鹰击【绽放印】
      "239": 0.25, //鹰击【神速印】
      "240": 0.1, //鹰击【感应印】
      "241": 0.05 //鹰击【强健印】
    },
    "21": { //黄泉旅者
      "242": 1 //黄泉旅者【转换印】
    },
    "22": { //狂涛泉涌
      "243": 0.35, //狂涛泉涌【一闪印】
      "244": 0.5, //狂涛泉涌【振奋印】
      "245": 0.15 //狂涛泉涌【信念印】
    },
    "23": { //修罗降临
      "246": 1 //修罗降临【拯救印】
    },
    "24": { //罗刹降临
      "247": 1 //罗刹降临【致命印】
    },
    "25": { //深渊苦海
      "248": 0.6, //深渊苦海【洞察印】
      "249": 0.3, //深渊苦海【破甲印】
      "250": 0.1 //深渊苦海【践踏印】
    },
    "26": { //日闪
      "251": 0.4, //日闪【震击印】
      "252": 0.4, //日闪【刚毅印】
      "253": 0.2 //日闪【痛苦印】
    },
    "27": { //风之闪避
      "254": 0.9, //风之闪避【愈合印】
      "255": 0.1 //风之闪避【坚壁印】
    },
    "28": { //风之守护
      "256": 0.9, //风之守护【专注印】
      "257": 0.1 //风之守护【应激印】
    }
  },
  "count5": 2, //战士2铭文
  "group5": {
    "1": { //基本剑术
      "133": 0.3, //基本剑术【旋风印】
      "134": 0.4, //基本剑术【主宰印】
      "135": 0.1, //基本剑术【幽速印】
      "136": 0.2 //基本剑术【压制印】
    },
    "2": { //攻杀剑术
      "137": 0.6, //攻杀剑术【银光印】
      "138": 0.3, //攻杀剑术【暴君印】
      "139": 0.05, //攻杀剑术【血杀印】
      "140": 0.05 //攻杀剑术【煌龙印】
    },
    "3": { //刺杀剑术
      "141": 0.2, //刺杀剑术【耀光印】
      "142": 0.8 //刺杀剑术【破山印】
    },
    "4": { //半月弯刀
      "143": 0.65, //半月弯刀【月华印】
      "144": 0.25, //半月弯刀【观月印】
      "145": 0.1 //半月弯刀【疾月印】
    },
    "5": { //野蛮冲撞
      "146": 0.15, //野蛮冲撞【裂风印】
      "147": 0.05, //野蛮冲撞【聚火印】
      "148": 0.05, //野蛮冲撞【疾步印】
      "149": 0.30, //野蛮冲撞【冲撞印】
      "150": 0.45 //野蛮冲撞【蛮勇印】
    },
    "6": { //烈火剑法
      "151": 0.45, //烈火剑法【斩月印】
      "152": 0.5, //烈火剑法【夺火印】
      "153": 0.05 //烈火剑法【燃烧印】
    },
    "7": { //翔空剑法
      "154": 0.5, //翔空剑法【开疆印】
      "155": 0.3, //翔空剑法【神躯印】
      "156": 0.2 //翔空剑法【升龙印】
    },
    "8": { //莲月剑法
      "161": 0.75, //十方斩【增强印】
      "162": 0.25 //十方斩【强大印】
    },
    "9": { //快刀斩马
      "163": 0.5, //快刀斩马【刀法印】
      "164": 0.3, //快刀斩马【快刀印】
      "165": 0.2 //快刀斩马【霸刀印】
    },
    "10": { //天雷锤
      "166": 0.8, //天雷锤【锤子印】
      "167": 0.15, //天雷锤【战锤印】
      "168": 0.05 //天雷锤【天神印】
    },
    "11": { //铁布衫
      "169": 0.75, //铁布衫【健壮印】
      "170": 0.25 //铁布衫【贴布印】
    },
    "12": { //乾坤大挪移
      "171": 1 //乾坤大挪移【挪移印】
    },
    "13": { //斗转星移
      "172": 1 //斗转星移【斗转印】
    },
    "14": { //破血狂杀
      "173": 0.1, //破血狂杀【破血印】
      "174": 0.9 //破血狂杀【狂魔印】
    },
    "15": { //金刚之躯
      "175": 0.55, //金刚之躯【金刚印】
      "176": 0.45 //金刚之躯【苏铭印】
    },
    "16": { //移花接木
      "177": 0.55, //移花接木【敬畏印】
      "178": 0.45 //移花接木【回声印】
    },
    "17": { //挑衅
      "197": 0.7, //挑衅【心眼印】
      "198": 0.2, //挑衅【虚空印】
      "199": 0.1 //挑衅【狩猎印】
    },
    "18": { //泰山压顶
      "177": 0.75, //泰山压顶【调和印】
      "178": 0.25 //泰山压顶【怜悯印】
    },
    "19": { //莲月剑法
      "157": 0.95, //莲月剑法【莲月印】
      "158": 0.05 //莲月剑法【无双印】
    }
  },
  "count6": 2, //法师2铭文
  "group6": {
    "1": { //火球术
      "91": 0.9, //火球术【火锥印】
      "92": 0.1 //火球术【火球印】
    },
    "2": { //霹雳掌
      "93": 0.6, //霹雳掌【超凡印】
      "94": 0.4 //霹雳掌【异端印】
    },
    "3": { //冰月神掌
      "95": 0.9, //冰月神掌【冰雪印】
      "96": 0.1 //冰月神掌【冰强印】
    },
    "4": { //抗拒火环
      "98": 0.1, //抗拒火环【焰华印】
      "99": 0.9 //抗拒火环【火环印】
    },
    "5": { //诱惑之光
      "100": 0.1, //诱惑之光【军势印】
      "101": 0.4, //诱惑之光【魔语印】
      "102": 0.4, //诱惑之光【魔魇印】
      "103": 0.1 //诱惑之光【血契印】
    },
    "6": { //瞬息移动
      "104": 0.8, //瞬息移动【移动印】
      "196": 0.2 //瞬息移动【移速印】
    },
    "7": { //大火球
      "105": 0.7, //大火球【训诫印】
      "106": 0.2, //大火球【堕落印】
      "107": 0.1 //大火球【触媒印】
    },
    "8": { //雷电术
      "108": 0.3, //雷电术【天罚印】
      "109": 0.15, //雷电术【天怒印】
      "110": 0.55 //雷电术【不灭印】
    },
    "9": { //冰月震天
      "111": 1 //冰月震天【弧光印】
    },
    "10": { //击风
      "112": 1 //击风【静默印】
    },
    "11": { //地狱火
      "113": 1 //地狱火【炎龙印】
    },
    "12": { //疾光电影
      "114": 0.6, //疾光电影【雷神印】
      "115": 0.35, //疾光电影【雷诛印】
      "116": 0.05 //疾光电影【雷咒印】
    },
    "13": { //冰沙掌
      "117": 0.25, //冰沙掌【冰刀印】
      "118": 0.75 //冰沙掌【冰霜印】 
    },
    "14": { //风震天
      "119": 0.2, //风震天【风波印】
      "120": 0.8 //风震天【山风印】
    },
    "15": { //火墙
      "121": 0.8, //火墙【观火印】
      "122": 0.2 //火墙【真红印】
    },
    "16": { //圣言术
      "123": 0.15, //圣言术【圣灵印】
      "124": 0.85 //圣言术【秘咒印】
    },
    "17": { //移形换位
      "125": 1 //移形换位【移行印】
    },
    "18": { //魔法盾
      "126": 0.7, //魔法盾【天守印】
      "127": 0.15, //魔法盾【霜骨印】
      "128": 0.15 //魔法盾【逢生印】
    },
    "19": { //爆裂火焰
      "129": 1 //爆裂火焰【疾火印】
    },
    "20": { //地狱雷光
      "130": 1 //地狱雷光【雷龙印】
    },
    "21": { //冰咆哮
      "131": 0.8, //冰咆哮【龙行印】
      "132": 0.2 //冰咆哮【龙魂印】
    },
    "22": { //焰天火雨
      "179": 0.7, //焰天火雨【焰天印】
      "180": 0.2, //焰天火雨【群火印】
      "181": 0.1 //焰天火雨【爆火印】
    },
    "23": { //天之怒火
      "182": 0.8, //天之怒火【圣人印】
      "183": 0.2 //天之怒火【怒火印】
    },
    "24": { //魄冰刺
      "184": 0.8, //魄冰刺【冰刺印】
      "185": 0.2 //魄冰刺【冰花印】
    },
    "25": { //护身冰环
      "186": 0.7, //护身冰环【冰神印】
      "187": 0.3 //护身冰环【冰环印】
    },
    "26": { //怒神霹雳
      "188": 1 //怒神霹雳【霹雳印】
    },
    "27": { //天打雷劈
      "189": 0.8, //天打雷劈【正义印】
      "190": 0.2 //天打雷劈【反击印】
    },
    "28": { //闪电雷鸣
      "191": 1 //闪电雷鸣【命中印】
    },
    "29": { //龙卷风
      "192": 0.8, //龙卷风【风暴印】
      "193": 0.2 //龙卷风【暴风印】
    },
    "30": { //旋风墙
      "194": 0.8, //旋风墙【崩坏印】
      "195": 0.2 //旋风墙【风怒印】
    }
  },
  "count7": 2, //道士2铭文
  "group7": {
    "1": { //治愈术
      "2": 0.75, //治愈术【神术印】
      "3": 0.15, //治愈术【神宝印】
      "4": 0.1 //治愈术【妙手印】
    },
    "2": { //精神力战法
      "5": 0.75, //精神力战法【灵击印】
      "6": 0.2, //精神力战法【道法印】
      "7": 0.05 //精神力战法【灵爆印】
    },
    "3": { //施毒术
      "8": 0.15, //施毒术【凌波印】
      "9": 0.65, //施毒术【凌锋印】
      "10": 0.1, //施毒术【凌云印】
      "11": 0.1 //施毒术【凌蛊印】
    },
    "4": { //灵魂火符
      "12": 0.5, //灵魂火符【火蛇印】
      "13": 0.1, //灵魂火符【弹射印】
      "68": 0.05, //灵魂火符【群射印】
      "14": 0.3, //灵魂火符【灵控印】
      "15": 0.05 //灵魂火符【符阵印】
    },
    "5": { //月魂断玉
      "16": 0.25, //月魂断玉【玉龙印】
      "17": 0.75 //月魂断玉【龙王印】
    },
    "6": { //召唤骷髅
      "18": 0.15, //召唤骷髅【君王印】
      "19": 0.15, //召唤骷髅【偷天印】
      "20": 0.7 //召唤骷髅【迦兰印】
    },
    "7": { //隐身术
      "21": 0.1, //隐身术【空相印】
      "22": 0.9 //隐身术【流星印】
    },
    "8": { //幽灵盾
      "23": 0.3, //幽灵盾【灵携印】
      "24": 0.6, //幽灵盾【灵保印】
      "25": 0.1 //幽灵盾【幽强印】
    },
    "9": { //集体隐身术
      "26": 0.9, //集体隐身术【影集印】
      "27": 0.1 //集体隐身术【集中印】
    },
    "10": { //月魂灵波
      "28": 0.5, //月魂灵波【毒蛇印】
      "29": 0.25, //月魂灵波【蛇射印】
      "69": 0.05, //月魂灵波【枪射印】
      "30": 0.15, //月魂灵波【魂控印】
      "31": 0.05 //月魂灵波【魂阵印】
    },
    "11": { //神圣战甲术
      "32": 0.15, //神圣战甲术【凝丹印】
      "33": 0.75, //神圣战甲术【凝保印】
      "34": 0.1 //神圣战甲术【凝效印】
    },
    "12": { //困魔咒
      "35": 0.1, //困魔咒【邪咒印】
      "36": 0.9 //困魔咒【正咒印】
    },
    "13": { //空拳刀法
      "37": 0.55, //空拳刀法【空拳印】
      "38": 0.35, //空拳刀法【拳霸印】
      "39": 0.1 //空拳刀法【拳击印】
    },
    "14": { //强魔震法
      "40": 0.1, //强魔震法【强法印】
      "41": 0.9 //强魔震法【强保印】
    },
    "15": { //召唤神兽
      "42": 0.75, //召唤神兽【灵兽印】
      "43": 0.15, //召唤神兽【血兽印】
      "44": 0.1 //召唤神兽【圣兽印】
    },
    "16": { //群体治愈术
      "45": 1 //群体治愈术【瑶光印】
    },
    "17": { //超强召唤骷髅
      "46": 0.1, //超强召唤骷髅【君王印】
      "47": 0.15, //超强召唤骷髅【偷天印】
      "48": 0.75 //超强召唤骷髅【迦兰印】
    },
    "18": { //猛虎强势
      "49": 0.9, //猛虎强势【猛士印】
      "50": 0.1 //猛虎强势【强势印】
    },
    "19": {
      "51": 0.85, //回生术【保护印】
      "52": 0.15 //回生术【道尊印】
    },
    "20": { //移花接玉
      "53": 0.6, //移花接玉【接速印】
      "54": 0.4 //移花接玉【轮回印】
    },
    "21": { //妙影无踪【踪保印】
      "55": 0.85, //妙影无踪【踪保印】
      "70": 0.15 //妙影无踪【妙影印】
    },
    "22": { //灭魂火符
      "56": 0.5, //灭魂火符【速射印】
      "57": 0.25, //灭魂火符【爆射印】
      "58": 0.15, //灭魂火符【灭魂印】
      "59": 0.05, //灭魂火符【灭阵印】
      "71": 0.05 //灭魂火符【弓射印】
    },
    "23": { //炎魔召唤术
      "60": 0.50, //炎魔召唤术【红月印】
      "61": 0.25, //炎魔召唤术【火焰印】
      "62": 0.25 //炎魔召唤术【真强印】
    },
    "24": { //魔焰强解术
      "63": 0.75, //魔焰强解术【凶兆印】
      "64": 0.15, //魔焰强解术【祸源印】
      "65": 0.1 //魔焰强解术【宿命印】
    },
    "25": { //传染
      "66": 0.85, //传染【射手印】
      "67": 0.15 //传染【传射印】
    },
    "26": { //云寂术
      "72": 1 //云寂术【云寂印】
    },
    "27": { //阴阳法环
      "73": 0.55, //阴阳法环【吸血印】
      "74": 0.3, //阴阳法环【法环印】
      "75": 0.15 //阴阳法环【饮血印】
    },
    "28": { //吸星大法
      "76": 0.65, //吸星大法【吸星印】
      "77": 0.2, //吸星大法【血饮印】
      "78": 0.15 //吸星大法【咒语印】
    },
    "29": { //地狱回疗
      "79": 1 //地狱回疗【地狱印】
    }
  },
  "count8": 2, //刺客2铭文
  "group8": {
    "1": { //垂柳舞
      "202": 1 //垂柳舞【长生印】
    },
    "2": { //蔓藤舞
      "203": 1 //蔓藤舞【夺萃印】
    },
    "3": { //磨炼
      "204": 0.9, //磨炼【隐匿印】
      "205": 0.1 //磨炼【贪婪印】
    },
    "4": { //毒云
      "206": 0.9, //毒云【灵山印】
      "207": 0.1 //毒云【均衡印】
    },
    "5": { //盛开
      "208": 0.7, //盛开【冥想印】
      "209": 0.2, //盛开【纷争印】
      "210": 0.1 //盛开【异变印】
    },
    "6": { //白莲
      "211": 0.7, //白莲【野性印】
      "212": 0.2, //白莲【潜能印】
      "213": 0.1 //白莲【侵蚀印】
    },
    "7": { //满月恶狼
      "214": 1 //满月恶狼【献祭印】
    },
    "8": { //亡灵束缚
      "215": 1 //亡灵束缚【憎恶印】
    },
    "9": { //红莲
      "216": 0.7, //红莲【庇护印】
      "217": 0.2, //红莲【奇袭印】
      "218": 0.1 //红莲【无畏印】
    },
    "10": { //烈焰
      "219": 0.7, //烈焰【铁躯印】
      "220": 0.2, //烈焰【滋生印】
      "221": 0.1 //烈焰【吞噬印】
    },
    "11": { //血禅
      "222": 1 //血禅【急救印】
    },
    "12": { //血之盟约
      "223": 1 //血之盟约【渴血印】
    },
    "13": { //月季
      "224": 0.75, //月季【复苏印】
      "225": 0.2, //月季【刹那印】
      "226": 0.05 //月季【惩戒印】
    },
    "14": { //亡灵替身
      "227": 0.8, //亡灵替身【气数印】
      "228": 0.2 //亡灵替身【狂热印】
    },
    "15": { //孽报
      "229": 0.7, //孽报【阳炎印】
      "230": 0.2, //孽报【戒律印】
      "231": 0.1 //孽报【荆棘印】
    },
    "16": { //神机妙算
      "232": 1 //神机妙算【暴戾印】
    },
    "17": { //深渊
      "233": 1 //深渊【衰败印】
    },
    "18": { //新月爆炎龙
      "234": 0.85, //新月爆炎龙【突进印】
      "235": 0.1, //新月爆炎龙【收割印】
      "236": 0.05 //新月爆炎龙【破魔印】
    },
    "19": { //百花盛开
      "237": 1 //百花盛开【贯穿印】
    },
    "20": { //鹰击
      "238": 0.6, //鹰击【绽放印】
      "239": 0.25, //鹰击【神速印】
      "240": 0.1, //鹰击【感应印】
      "241": 0.05 //鹰击【强健印】
    },
    "21": { //黄泉旅者
      "242": 1 //黄泉旅者【转换印】
    },
    "22": { //狂涛泉涌
      "243": 0.35, //狂涛泉涌【一闪印】
      "244": 0.5, //狂涛泉涌【振奋印】
      "245": 0.15 //狂涛泉涌【信念印】
    },
    "23": { //修罗降临
      "246": 1 //修罗降临【拯救印】
    },
    "24": { //罗刹降临
      "247": 1 //罗刹降临【致命印】
    },
    "25": { //深渊苦海
      "248": 0.6, //深渊苦海【洞察印】
      "249": 0.3, //深渊苦海【破甲印】
      "250": 0.1 //深渊苦海【践踏印】
    },
    "26": { //日闪
      "251": 0.4, //日闪【震击印】
      "252": 0.4, //日闪【刚毅印】
      "253": 0.2 //日闪【痛苦印】
    },
    "27": { //风之闪避
      "254": 0.9, //风之闪避【愈合印】
      "255": 0.1 //风之闪避【坚壁印】
    },
    "28": { //风之守护
      "256": 0.9, //风之守护【专注印】
      "257": 0.1 //风之守护【应激印】
    }
  },
  "count9": 1, //战士1铭文
  "group9": {
    "1": { //基本剑术
      "133": 0.3, //基本剑术【旋风印】
      "134": 0.4, //基本剑术【主宰印】
      "135": 0.1, //基本剑术【幽速印】
      "136": 0.2 //基本剑术【压制印】
    },
    "2": { //攻杀剑术
      "137": 0.6, //攻杀剑术【银光印】
      "138": 0.3, //攻杀剑术【暴君印】
      "139": 0.05, //攻杀剑术【血杀印】
      "140": 0.05 //攻杀剑术【煌龙印】
    },
    "3": { //刺杀剑术
      "141": 0.2, //刺杀剑术【耀光印】
      "142": 0.8 //刺杀剑术【破山印】
    },
    "4": { //半月弯刀
      "143": 0.65, //半月弯刀【月华印】
      "144": 0.25, //半月弯刀【观月印】
      "145": 0.1 //半月弯刀【疾月印】
    },
    "5": { //野蛮冲撞
      "146": 0.15, //野蛮冲撞【裂风印】
      "147": 0.05, //野蛮冲撞【聚火印】
      "148": 0.05, //野蛮冲撞【疾步印】
      "149": 0.30, //野蛮冲撞【冲撞印】
      "150": 0.45 //野蛮冲撞【蛮勇印】
    },
    "6": { //烈火剑法
      "151": 0.45, //烈火剑法【斩月印】
      "152": 0.5, //烈火剑法【夺火印】
      "153": 0.05 //烈火剑法【燃烧印】
    },
    "7": { //翔空剑法
      "154": 0.5, //翔空剑法【开疆印】
      "155": 0.3, //翔空剑法【神躯印】
      "156": 0.2 //翔空剑法【升龙印】
    },
    "8": { //莲月剑法
      "161": 0.75, //十方斩【增强印】
      "162": 0.25 //十方斩【强大印】
    },
    "9": { //快刀斩马
      "163": 0.5, //快刀斩马【刀法印】
      "164": 0.3, //快刀斩马【快刀印】
      "165": 0.2 //快刀斩马【霸刀印】
    },
    "10": { //天雷锤
      "166": 0.8, //天雷锤【锤子印】
      "167": 0.15, //天雷锤【战锤印】
      "168": 0.05 //天雷锤【天神印】
    },
    "11": { //铁布衫
      "169": 0.75, //铁布衫【健壮印】
      "170": 0.25 //铁布衫【贴布印】
    },
    "12": { //乾坤大挪移
      "171": 1 //乾坤大挪移【挪移印】
    },
    "13": { //斗转星移
      "172": 1 //斗转星移【斗转印】
    },
    "14": { //破血狂杀
      "173": 0.1, //破血狂杀【破血印】
      "174": 0.9 //破血狂杀【狂魔印】
    },
    "15": { //金刚之躯
      "175": 0.55, //金刚之躯【金刚印】
      "176": 0.45 //金刚之躯【苏铭印】
    },
    "16": { //移花接木
      "177": 0.55, //移花接木【敬畏印】
      "178": 0.45 //移花接木【回声印】
    },
    "17": { //挑衅
      "197": 0.7, //挑衅【心眼印】
      "198": 0.2, //挑衅【虚空印】
      "199": 0.1 //挑衅【狩猎印】
    },
    "18": { //泰山压顶
      "177": 0.75, //泰山压顶【调和印】
      "178": 0.25 //泰山压顶【怜悯印】
    },
    "19": { //莲月剑法
      "157": 0.95, //莲月剑法【莲月印】
      "158": 0.05 //莲月剑法【无双印】
    }
  },
  "count10": 1, //法师1铭文
  "group10": {
    "1": { //火球术
      "91": 0.9, //火球术【火锥印】
      "92": 0.1 //火球术【火球印】
    },
    "2": { //霹雳掌
      "93": 0.6, //霹雳掌【超凡印】
      "94": 0.4 //霹雳掌【异端印】
    },
    "3": { //冰月神掌
      "95": 0.9, //冰月神掌【冰雪印】
      "96": 0.1 //冰月神掌【冰强印】
    },
    "4": { //抗拒火环
      "98": 0.1, //抗拒火环【焰华印】
      "99": 0.9 //抗拒火环【火环印】
    },
    "5": { //诱惑之光
      "100": 0.1, //诱惑之光【军势印】
      "101": 0.4, //诱惑之光【魔语印】
      "102": 0.4, //诱惑之光【魔魇印】
      "103": 0.1 //诱惑之光【血契印】
    },
    "6": { //瞬息移动
      "104": 0.8, //瞬息移动【移动印】
      "196": 0.2 //瞬息移动【移速印】
    },
    "7": { //大火球
      "105": 0.7, //大火球【训诫印】
      "106": 0.2, //大火球【堕落印】
      "107": 0.1 //大火球【触媒印】
    },
    "8": { //雷电术
      "108": 0.3, //雷电术【天罚印】
      "109": 0.15, //雷电术【天怒印】
      "110": 0.55 //雷电术【不灭印】
    },
    "9": { //冰月震天
      "111": 1 //冰月震天【弧光印】
    },
    "10": { //击风
      "112": 1 //击风【静默印】
    },
    "11": { //地狱火
      "113": 1 //地狱火【炎龙印】
    },
    "12": { //疾光电影
      "114": 0.6, //疾光电影【雷神印】
      "115": 0.35, //疾光电影【雷诛印】
      "116": 0.05 //疾光电影【雷咒印】
    },
    "13": { //冰沙掌
      "117": 0.25, //冰沙掌【冰刀印】
      "118": 0.75 //冰沙掌【冰霜印】 
    },
    "14": { //风震天
      "119": 0.2, //风震天【风波印】
      "120": 0.8 //风震天【山风印】
    },
    "15": { //火墙
      "121": 0.8, //火墙【观火印】
      "122": 0.2 //火墙【真红印】
    },
    "16": { //圣言术
      "123": 0.15, //圣言术【圣灵印】
      "124": 0.85 //圣言术【秘咒印】
    },
    "17": { //移形换位
      "125": 1 //移形换位【移行印】
    },
    "18": { //魔法盾
      "126": 0.7, //魔法盾【天守印】
      "127": 0.15, //魔法盾【霜骨印】
      "128": 0.15 //魔法盾【逢生印】
    },
    "19": { //爆裂火焰
      "129": 1 //爆裂火焰【疾火印】
    },
    "20": { //地狱雷光
      "130": 1 //地狱雷光【雷龙印】
    },
    "21": { //冰咆哮
      "131": 0.8, //冰咆哮【龙行印】
      "132": 0.2 //冰咆哮【龙魂印】
    },
    "22": { //焰天火雨
      "179": 0.7, //焰天火雨【焰天印】
      "180": 0.2, //焰天火雨【群火印】
      "181": 0.1 //焰天火雨【爆火印】
    },
    "23": { //天之怒火
      "182": 0.8, //天之怒火【圣人印】
      "183": 0.2 //天之怒火【怒火印】
    },
    "24": { //魄冰刺
      "184": 0.8, //魄冰刺【冰刺印】
      "185": 0.2 //魄冰刺【冰花印】
    },
    "25": { //护身冰环
      "186": 0.7, //护身冰环【冰神印】
      "187": 0.3 //护身冰环【冰环印】
    },
    "26": { //怒神霹雳
      "188": 1 //怒神霹雳【霹雳印】
    },
    "27": { //天打雷劈
      "189": 0.8, //天打雷劈【正义印】
      "190": 0.2 //天打雷劈【反击印】
    },
    "28": { //闪电雷鸣
      "191": 1 //闪电雷鸣【命中印】
    },
    "29": { //龙卷风
      "192": 0.8, //龙卷风【风暴印】
      "193": 0.2 //龙卷风【暴风印】
    },
    "30": { //旋风墙
      "194": 0.8, //旋风墙【崩坏印】
      "195": 0.2 //旋风墙【风怒印】
    }
  },
  "count11": 1, //道士1铭文
  "group11": {
    "1": { //治愈术
      "2": 0.75, //治愈术【神术印】
      "3": 0.15, //治愈术【神宝印】
      "4": 0.1 //治愈术【妙手印】
    },
    "2": { //精神力战法
      "5": 0.75, //精神力战法【灵击印】
      "6": 0.2, //精神力战法【道法印】
      "7": 0.05 //精神力战法【灵爆印】
    },
    "3": { //施毒术
      "8": 0.15, //施毒术【凌波印】
      "9": 0.65, //施毒术【凌锋印】
      "10": 0.1, //施毒术【凌云印】
      "11": 0.1 //施毒术【凌蛊印】
    },
    "4": { //灵魂火符
      "12": 0.5, //灵魂火符【火蛇印】
      "13": 0.1, //灵魂火符【弹射印】
      "68": 0.05, //灵魂火符【群射印】
      "14": 0.3, //灵魂火符【灵控印】
      "15": 0.05 //灵魂火符【符阵印】
    },
    "5": { //月魂断玉
      "16": 0.25, //月魂断玉【玉龙印】
      "17": 0.75 //月魂断玉【龙王印】
    },
    "6": { //召唤骷髅
      "18": 0.15, //召唤骷髅【君王印】
      "19": 0.15, //召唤骷髅【偷天印】
      "20": 0.7 //召唤骷髅【迦兰印】
    },
    "7": { //隐身术
      "21": 0.1, //隐身术【空相印】
      "22": 0.9 //隐身术【流星印】
    },
    "8": { //幽灵盾
      "23": 0.3, //幽灵盾【灵携印】
      "24": 0.6, //幽灵盾【灵保印】
      "25": 0.1 //幽灵盾【幽强印】
    },
    "9": { //集体隐身术
      "26": 0.9, //集体隐身术【影集印】
      "27": 0.1 //集体隐身术【集中印】
    },
    "10": { //月魂灵波
      "28": 0.5, //月魂灵波【毒蛇印】
      "29": 0.25, //月魂灵波【蛇射印】
      "69": 0.05, //月魂灵波【枪射印】
      "30": 0.15, //月魂灵波【魂控印】
      "31": 0.05 //月魂灵波【魂阵印】
    },
    "11": { //神圣战甲术
      "32": 0.15, //神圣战甲术【凝丹印】
      "33": 0.75, //神圣战甲术【凝保印】
      "34": 0.1 //神圣战甲术【凝效印】
    },
    "12": { //困魔咒
      "35": 0.1, //困魔咒【邪咒印】
      "36": 0.9 //困魔咒【正咒印】
    },
    "13": { //空拳刀法
      "37": 0.55, //空拳刀法【空拳印】
      "38": 0.35, //空拳刀法【拳霸印】
      "39": 0.1 //空拳刀法【拳击印】
    },
    "14": { //强魔震法
      "40": 0.1, //强魔震法【强法印】
      "41": 0.9 //强魔震法【强保印】
    },
    "15": { //召唤神兽
      "42": 0.75, //召唤神兽【灵兽印】
      "43": 0.15, //召唤神兽【血兽印】
      "44": 0.1 //召唤神兽【圣兽印】
    },
    "16": { //群体治愈术
      "45": 1 //群体治愈术【瑶光印】
    },
    "17": { //超强召唤骷髅
      "46": 0.1, //超强召唤骷髅【君王印】
      "47": 0.15, //超强召唤骷髅【偷天印】
      "48": 0.75 //超强召唤骷髅【迦兰印】
    },
    "18": { //猛虎强势
      "49": 0.9, //猛虎强势【猛士印】
      "50": 0.1 //猛虎强势【强势印】
    },
    "19": {
      "51": 0.85, //回生术【保护印】
      "52": 0.15 //回生术【道尊印】
    },
    "20": { //移花接玉
      "53": 0.6, //移花接玉【接速印】
      "54": 0.4 //移花接玉【轮回印】
    },
    "21": { //妙影无踪【踪保印】
      "55": 0.85, //妙影无踪【踪保印】
      "70": 0.15 //妙影无踪【妙影印】
    },
    "22": { //灭魂火符
      "56": 0.5, //灭魂火符【速射印】
      "57": 0.25, //灭魂火符【爆射印】
      "58": 0.15, //灭魂火符【灭魂印】
      "59": 0.05, //灭魂火符【灭阵印】
      "71": 0.05 //灭魂火符【弓射印】
    },
    "23": { //炎魔召唤术
      "60": 0.50, //炎魔召唤术【红月印】
      "61": 0.25, //炎魔召唤术【火焰印】
      "62": 0.25 //炎魔召唤术【真强印】
    },
    "24": { //魔焰强解术
      "63": 0.75, //魔焰强解术【凶兆印】
      "64": 0.15, //魔焰强解术【祸源印】
      "65": 0.1 //魔焰强解术【宿命印】
    },
    "25": { //传染
      "66": 0.85, //传染【射手印】
      "67": 0.15 //传染【传射印】
    },
    "26": { //云寂术
      "72": 1 //云寂术【云寂印】
    },
    "27": { //阴阳法环
      "73": 0.55, //阴阳法环【吸血印】
      "74": 0.3, //阴阳法环【法环印】
      "75": 0.15 //阴阳法环【饮血印】
    },
    "28": { //吸星大法
      "76": 0.65, //吸星大法【吸星印】
      "77": 0.2, //吸星大法【血饮印】
      "78": 0.15 //吸星大法【咒语印】
    },
    "29": { //地狱回疗
      "79": 1 //地狱回疗【地狱印】
    }
  },
  "count12": 1, //刺客1铭文
  "group12": {
    "1": { //垂柳舞
      "202": 1 //垂柳舞【长生印】
    },
    "2": { //蔓藤舞
      "203": 1 //蔓藤舞【夺萃印】
    },
    "3": { //磨炼
      "204": 0.9, //磨炼【隐匿印】
      "205": 0.1 //磨炼【贪婪印】
    },
    "4": { //毒云
      "206": 0.9, //毒云【灵山印】
      "207": 0.1 //毒云【均衡印】
    },
    "5": { //盛开
      "208": 0.7, //盛开【冥想印】
      "209": 0.2, //盛开【纷争印】
      "210": 0.1 //盛开【异变印】
    },
    "6": { //白莲
      "211": 0.7, //白莲【野性印】
      "212": 0.2, //白莲【潜能印】
      "213": 0.1 //白莲【侵蚀印】
    },
    "7": { //满月恶狼
      "214": 1 //满月恶狼【献祭印】
    },
    "8": { //亡灵束缚
      "215": 1 //亡灵束缚【憎恶印】
    },
    "9": { //红莲
      "216": 0.7, //红莲【庇护印】
      "217": 0.2, //红莲【奇袭印】
      "218": 0.1 //红莲【无畏印】
    },
    "10": { //烈焰
      "219": 0.7, //烈焰【铁躯印】
      "220": 0.2, //烈焰【滋生印】
      "221": 0.1 //烈焰【吞噬印】
    },
    "11": { //血禅
      "222": 1 //血禅【急救印】
    },
    "12": { //血之盟约
      "223": 1 //血之盟约【渴血印】
    },
    "13": { //月季
      "224": 0.75, //月季【复苏印】
      "225": 0.2, //月季【刹那印】
      "226": 0.05 //月季【惩戒印】
    },
    "14": { //亡灵替身
      "227": 0.8, //亡灵替身【气数印】
      "228": 0.2 //亡灵替身【狂热印】
    },
    "15": { //孽报
      "229": 0.7, //孽报【阳炎印】
      "230": 0.2, //孽报【戒律印】
      "231": 0.1 //孽报【荆棘印】
    },
    "16": { //神机妙算
      "232": 1 //神机妙算【暴戾印】
    },
    "17": { //深渊
      "233": 1 //深渊【衰败印】
    },
    "18": { //新月爆炎龙
      "234": 0.85, //新月爆炎龙【突进印】
      "235": 0.1, //新月爆炎龙【收割印】
      "236": 0.05 //新月爆炎龙【破魔印】
    },
    "19": { //百花盛开
      "237": 1 //百花盛开【贯穿印】
    },
    "20": { //鹰击
      "238": 0.6, //鹰击【绽放印】
      "239": 0.25, //鹰击【神速印】
      "240": 0.1, //鹰击【感应印】
      "241": 0.05 //鹰击【强健印】
    },
    "21": { //黄泉旅者
      "242": 1 //黄泉旅者【转换印】
    },
    "22": { //狂涛泉涌
      "243": 0.35, //狂涛泉涌【一闪印】
      "244": 0.5, //狂涛泉涌【振奋印】
      "245": 0.15 //狂涛泉涌【信念印】
    },
    "23": { //修罗降临
      "246": 1 //修罗降临【拯救印】
    },
    "24": { //罗刹降临
      "247": 1 //罗刹降临【致命印】
    },
    "25": { //深渊苦海
      "248": 0.6, //深渊苦海【洞察印】
      "249": 0.3, //深渊苦海【破甲印】
      "250": 0.1 //深渊苦海【践踏印】
    },
    "26": { //日闪
      "251": 0.4, //日闪【震击印】
      "252": 0.4, //日闪【刚毅印】
      "253": 0.2 //日闪【痛苦印】
    },
    "27": { //风之闪避
      "254": 0.9, //风之闪避【愈合印】
      "255": 0.1 //风之闪避【坚壁印】
    },
    "28": { //风之守护
      "256": 0.9, //风之守护【专注印】
      "257": 0.1 //风之守护【应激印】
    }
  }
}